crossfit/__init__.py
crossfit/bin/tools/jacococli.jar
crossfit/commands/__init__.py
crossfit/commands/command.py
crossfit/commands/command_builder.py
crossfit/executors/__init__.py
crossfit/executors/executor.py
crossfit/executors/executor_factory.py
crossfit/executors/local_executor.py
crossfit/models/__init__.py
crossfit/models/command_models.py
crossfit/models/executor_models.py
crossfit/models/tool_models.py
crossfit/refs/__init__.py
crossfit/tools/__init__.py
crossfit/tools/dotnet_coverage.py
crossfit/tools/jacoco.py
crossfit/tools/tool.py
crossfit/tools/tool_factory.py
smokecrossfit-0.0.0.dist-info/METADATA
smokecrossfit-0.0.0.dist-info/WHEEL
smokecrossfit-0.0.0.dist-info/top_level.txt
smokecrossfit-0.0.0.dist-info/RECORD
