Metadata-Version: 2.4
Name: SmokeCrossFit
Version: 0.0.0
Summary: A unified interface for various code coverage tools (JaCoCo, dotnet-coverage)
Requires-Python: >=3.12
